Metadata-Version: 2.1
Name: readi
Version: 0.1.0
Summary: Dead simple class/function registration.
Home-page: https://github.com/beasteers/readi
Author: Bea Steers
Author-email: bea.steers@gmail.com
License: MIT License
Keywords: simple class function registration entrypoints setup.py register collection
Platform: UNKNOWN
